[
    {
      "Body": {
        "stkCallback": {
          "MerchantRequestID": "c4dd-4669-a173-d5cee84d66e91738837",
          "CheckoutRequestID": "ws_CO_06032024201415158799993420",
          "ResultCode": 1032,
          "ResultDesc": "Request cancelled by user"
        }
      }
    },
    {
      "Body": {
        "stkCallback": {
          "MerchantRequestID": "c0d2-4b9a-a71a-12bae346ef6e417798",
          "CheckoutRequestID": "ws_CO_07032024171605268799993420",
          "ResultCode": 1037,
          "ResultDesc": "DS timeout user cannot be reached"
        }
      }
    }
  ]
  